{
	"$schema": "http://schema.management.azure.com/schemas/2015-01-01/deploymentTemplate.json#",
	"contentVersion": "1.0.0.0",
	"parameters": {
		"factoryName": {
			"type": "string",
			"metadata": "Data Factory name",
			"defaultValue": "EAL-MAIN-ADF"
		}
	},
	"variables": {
		"factoryId": "[concat('Microsoft.DataFactory/factories/', parameters('factoryName'))]"
	},
	"resources": [
		{
			"name": "[concat(parameters('factoryName'), '/PAIRINGITEMblobtoSQL')]",
			"type": "Microsoft.DataFactory/factories/dataflows",
			"apiVersion": "2018-06-01",
			"properties": {
				"folder": {
					"name": "Inactive"
				},
				"type": "MappingDataFlow",
				"typeProperties": {
					"sources": [
						{
							"dataset": {
								"referenceName": "SF_source_pairing_item",
								"type": "DatasetReference"
							},
							"name": "SFPairingItem"
						}
					],
					"sinks": [
						{
							"dataset": {
								"referenceName": "SQL_PAIRING_ITEM_TABLE",
								"type": "DatasetReference"
							},
							"name": "PARINGITEMtoSQL"
						}
					],
					"transformations": [
						{
							"name": "AddWrkflwIDandTS"
						}
					],
					"script": "parameters{\n\trun_id as string\n}\nsource(output(\n\t\tpairing_id as string,\n\t\tpairing_item_id as string,\n\t\tpairing_item_type as string,\n\t\tflight_id as string,\n\t\tshift_name as string,\n\t\tshift_start_time as string,\n\t\tshift_end_time as string,\n\t\tshift_type as string,\n\t\tshift_is_work as boolean,\n\t\tshift_is_reserve as boolean,\n\t\tshift_is_sick as boolean,\n\t\tshift_is_training as boolean,\n\t\tshift_is_vacation as boolean,\n\t\tupdated_at as string\n\t),\n\tallowSchemaDrift: true,\n\tvalidateSchema: false,\n\tignoreNoFilesFound: false,\n\tdocumentForm: 'documentPerLine') ~> SFPairingItem\nSFPairingItem derive(ADF_TIMESTAMP = currentTimestamp(),\n\t\tRUN_ID = $run_id) ~> AddWrkflwIDandTS\nAddWrkflwIDandTS sink(allowSchemaDrift: true,\n\tvalidateSchema: false,\n\tinput(\n\t\tpairing_id as string,\n\t\tpairing_item_id as string,\n\t\tpairing_item_type as string,\n\t\tflight_id as string,\n\t\tshift_name as string,\n\t\tshift_start_time as timestamp,\n\t\tshift_end_time as timestamp,\n\t\tshift_type as string,\n\t\tshift_is_work as boolean,\n\t\tshift_is_reserve as boolean,\n\t\tshift_is_sick as boolean,\n\t\tshift_is_training as boolean,\n\t\tshift_is_vacation as boolean,\n\t\tupdated_at as timestamp,\n\t\tADF_TIMESTAMP as timestamp,\n\t\tRUN_ID as string\n\t),\n\tdeletable:false,\n\tinsertable:true,\n\tupdateable:false,\n\tupsertable:false,\n\trecreate:true,\n\tformat: 'table',\n\tskipDuplicateMapInputs: true,\n\tskipDuplicateMapOutputs: true,\n\terrorHandlingOption: 'stopOnFirstError') ~> PARINGITEMtoSQL"
				}
			},
			"dependsOn": []
		},
		{
			"name": "[concat(parameters('factoryName'), '/PAIRINGblobtoSQL')]",
			"type": "Microsoft.DataFactory/factories/dataflows",
			"apiVersion": "2018-06-01",
			"properties": {
				"folder": {
					"name": "Inactive"
				},
				"type": "MappingDataFlow",
				"typeProperties": {
					"sources": [
						{
							"dataset": {
								"referenceName": "SF_source_pairing",
								"type": "DatasetReference"
							},
							"name": "SFPairing"
						}
					],
					"sinks": [
						{
							"dataset": {
								"referenceName": "SQL_PAIRING_TABLE",
								"type": "DatasetReference"
							},
							"name": "PARINGtoSQL"
						}
					],
					"transformations": [
						{
							"name": "AddWrkflwIDandTS"
						}
					],
					"script": "parameters{\n\trun_id as string\n}\nsource(output(\n\t\tpairing_id as string,\n\t\tuser_id as string,\n\t\tposition as string,\n\t\tname as string,\n\t\tdate as string,\n\t\tstart_date as string,\n\t\tend_date as string,\n\t\tupdated_at as string\n\t),\n\tallowSchemaDrift: true,\n\tvalidateSchema: false,\n\tignoreNoFilesFound: false,\n\tdocumentForm: 'documentPerLine') ~> SFPairing\nSFPairing derive(ADF_TIMESTAMP = currentTimestamp(),\n\t\tRUN_ID = $run_id) ~> AddWrkflwIDandTS\nAddWrkflwIDandTS sink(allowSchemaDrift: true,\n\tvalidateSchema: false,\n\tinput(\n\t\tdate as date,\n\t\tend_date as date,\n\t\tname as string,\n\t\tpairing_id as string,\n\t\tposition as string,\n\t\tstart_date as date,\n\t\tupdated_at as string,\n\t\tuser_id as string,\n\t\tADF_TIMESTAMP as timestamp,\n\t\tRUN_ID as string\n\t),\n\tdeletable:false,\n\tinsertable:true,\n\tupdateable:false,\n\tupsertable:false,\n\trecreate:true,\n\tformat: 'table',\n\tskipDuplicateMapInputs: true,\n\tskipDuplicateMapOutputs: true,\n\terrorHandlingOption: 'stopOnFirstError',\n\tmapColumn(\n\t\tdate,\n\t\tend_date,\n\t\tname,\n\t\tpairing_id,\n\t\tposition,\n\t\tstart_date,\n\t\tupdated_at,\n\t\tuser_id,\n\t\tADF_TIMESTAMP,\n\t\tRUN_ID\n\t)) ~> PARINGtoSQL"
				}
			},
			"dependsOn": []
		},
		{
			"name": "[concat(parameters('factoryName'), '/SHIFTblobtoSQL')]",
			"type": "Microsoft.DataFactory/factories/dataflows",
			"apiVersion": "2018-06-01",
			"properties": {
				"folder": {
					"name": "Inactive"
				},
				"type": "MappingDataFlow",
				"typeProperties": {
					"sources": [
						{
							"dataset": {
								"referenceName": "SF_source_shift",
								"type": "DatasetReference"
							},
							"name": "SFShift"
						}
					],
					"sinks": [
						{
							"dataset": {
								"referenceName": "SQL_SHIFT_TABLE",
								"type": "DatasetReference"
							},
							"name": "SHIFTtoSQL"
						}
					],
					"transformations": [
						{
							"name": "AddWrkflwIDandTS"
						}
					],
					"script": "parameters{\n\trun_id as string\n}\nsource(output(\n\t\tshift_id as string,\n\t\tuser_id as string,\n\t\tname as string,\n\t\tstart_time as string,\n\t\tend_time as string,\n\t\ttype as string,\n\t\tis_work as boolean,\n\t\tis_reserve as boolean,\n\t\tis_sick as boolean,\n\t\tis_training as boolean,\n\t\tis_vacation as boolean,\n\t\tupdated_at as string\n\t),\n\tallowSchemaDrift: true,\n\tvalidateSchema: false,\n\tignoreNoFilesFound: false,\n\tdocumentForm: 'documentPerLine') ~> SFShift\nSFShift derive(ADF_TIMESTAMP = currentTimestamp(),\n\t\tRUN_ID = $run_id) ~> AddWrkflwIDandTS\nAddWrkflwIDandTS sink(allowSchemaDrift: true,\n\tvalidateSchema: false,\n\tinput(\n\t\tshift_id as string,\n\t\tuser_id as string,\n\t\tname as string,\n\t\tstart_time as timestamp,\n\t\tend_time as timestamp,\n\t\ttype as string,\n\t\tis_work as boolean,\n\t\tis_reserve as boolean,\n\t\tis_sick as boolean,\n\t\tis_training as boolean,\n\t\tis_vacation as boolean,\n\t\tupdated_at as string,\n\t\tADF_TIMESTAMP as timestamp,\n\t\tRUN_ID as string\n\t),\n\tdeletable:false,\n\tinsertable:true,\n\tupdateable:false,\n\tupsertable:false,\n\trecreate:true,\n\tformat: 'table',\n\tskipDuplicateMapInputs: true,\n\tskipDuplicateMapOutputs: true,\n\terrorHandlingOption: 'stopOnFirstError') ~> SHIFTtoSQL"
				}
			},
			"dependsOn": []
		}
	]
}