{
	"$schema": "http://schema.management.azure.com/schemas/2015-01-01/deploymentTemplate.json#",
	"contentVersion": "1.0.0.0",
	"parameters": {
		"factoryName": {
			"type": "string",
			"metadata": "Data Factory name",
			"defaultValue": "EAL-MAIN-ADF"
		}
	},
	"variables": {
		"factoryId": "[concat('Microsoft.DataFactory/factories/', parameters('factoryName'))]"
	},
	"resources": [
		{
			"name": "[concat(parameters('factoryName'), '/Flt_nbr_range_matrix')]",
			"type": "Microsoft.DataFactory/factories/datasets",
			"apiVersion": "2018-06-01",
			"properties": {
				"linkedServiceName": {
					"referenceName": "eal_main_blob_connection",
					"type": "LinkedServiceReference"
				},
				"folder": {
					"name": "Azure blob"
				},
				"annotations": [],
				"type": "Excel",
				"typeProperties": {
					"sheetName": "FLT_NBR_RANGE",
					"location": {
						"type": "AzureBlobStorageLocation",
						"fileName": "FLT_NBR_RANGE.xlsx",
						"container": "flight-number-range"
					},
					"firstRowAsHeader": true
				},
				"schema": [
					{
						"name": "EFF_DATE",
						"type": "String"
					},
					{
						"name": "END_DATE",
						"type": "String"
					},
					{
						"name": "BEGIN_FLT_NBR",
						"type": "String"
					},
					{
						"name": "END_FLT_NBR",
						"type": "String"
					},
					{
						"name": "FLIGHT_TYPE",
						"type": "String"
					},
					{
						"name": "FLIGHT_SUBTYPE",
						"type": "String"
					},
					{
						"name": "FLT_TYPE_OPS_REPORT",
						"type": "String"
					}
				]
			},
			"dependsOn": []
		},
		{
			"name": "[concat(parameters('factoryName'), '/FltNbrRangeMatrixBlobToSQL')]",
			"type": "Microsoft.DataFactory/factories/dataflows",
			"apiVersion": "2018-06-01",
			"properties": {
				"folder": {
					"name": "PROD"
				},
				"type": "MappingDataFlow",
				"typeProperties": {
					"sources": [
						{
							"dataset": {
								"referenceName": "Flt_nbr_range_matrix",
								"type": "DatasetReference"
							},
							"name": "FltNbrMatrix"
						}
					],
					"sinks": [
						{
							"dataset": {
								"referenceName": "FLT_NBR_RANGE_PROD",
								"type": "DatasetReference"
							},
							"name": "FltNbrMatrixToSQL"
						}
					],
					"transformations": [
						{
							"name": "AddWrkflwIDandTS"
						}
					],
					"script": "parameters{\n\trun_id as string\n}\nsource(output(\n\t\tEFF_DATE as date 'yyyy-MM-dd',\n\t\tEND_DATE as date 'yyyy-MM-dd',\n\t\tBEGIN_FLT_NBR as integer '##0',\n\t\tEND_FLT_NBR as integer '##0',\n\t\tFLIGHT_TYPE as string,\n\t\tFLIGHT_SUBTYPE as string,\n\t\tFLT_TYPE_OPS_REPORT as string\n\t),\n\tallowSchemaDrift: true,\n\tvalidateSchema: false,\n\tignoreNoFilesFound: false) ~> FltNbrMatrix\nFltNbrMatrix derive(ADF_TIMESTAMP = currentTimestamp(),\n\t\tRUN_ID = $run_id) ~> AddWrkflwIDandTS\nAddWrkflwIDandTS sink(allowSchemaDrift: true,\n\tvalidateSchema: false,\n\tdeletable:false,\n\tinsertable:true,\n\tupdateable:false,\n\tupsertable:false,\n\trecreate:true,\n\tformat: 'table',\n\tskipDuplicateMapInputs: true,\n\tskipDuplicateMapOutputs: true,\n\terrorHandlingOption: 'stopOnFirstError') ~> FltNbrMatrixToSQL"
				}
			},
			"dependsOn": [
				"[concat(variables('factoryId'), '/datasets/Flt_nbr_range_matrix')]",
				"[concat(variables('factoryId'), '/datasets/FLT_NBR_RANGE_PROD')]"
			]
		},
		{
			"name": "[concat(parameters('factoryName'), '/FLT_NBR_RANGE_PROD')]",
			"type": "Microsoft.DataFactory/factories/datasets",
			"apiVersion": "2018-06-01",
			"properties": {
				"linkedServiceName": {
					"referenceName": "eal_edw_connection",
					"type": "LinkedServiceReference"
				},
				"annotations": [],
				"type": "AzureSqlTable",
				"schema": [],
				"typeProperties": {
					"schema": "dbo",
					"table": "FLT_NBR_RANGE_PROD"
				}
			},
			"dependsOn": []
		},
		{
			"name": "[concat(parameters('factoryName'), '/Flight_number_range_data')]",
			"type": "Microsoft.DataFactory/factories/pipelines",
			"apiVersion": "2018-06-01",
			"properties": {
				"activities": [
					{
						"name": "Flt_nbr_data_to_SQL",
						"type": "ExecuteDataFlow",
						"dependsOn": [],
						"policy": {
							"timeout": "1.00:00:00",
							"retry": 0,
							"retryIntervalInSeconds": 30,
							"secureOutput": false,
							"secureInput": false
						},
						"userProperties": [],
						"typeProperties": {
							"dataflow": {
								"referenceName": "FltNbrRangeMatrixBlobToSQL",
								"type": "DataFlowReference",
								"parameters": {
									"run_id": {
										"value": "'@{pipeline().RunId}'",
										"type": "Expression"
									}
								}
							},
							"compute": {
								"coreCount": 8,
								"computeType": "General"
							},
							"traceLevel": "Fine"
						}
					}
				],
				"variables": {
					"date": {
						"type": "String"
					}
				},
				"folder": {
					"name": "PROD"
				},
				"annotations": []
			},
			"dependsOn": [
				"[concat(variables('factoryId'), '/dataflows/FltNbrRangeMatrixBlobToSQL')]"
			]
		}
	]
}