{
	"$schema": "http://schema.management.azure.com/schemas/2015-01-01/deploymentTemplate.json#",
	"contentVersion": "1.0.0.0",
	"parameters": {
		"factoryName": {
			"type": "string",
			"metadata": "Data Factory name",
			"defaultValue": "EAL-MAIN-ADF"
		}
	},
	"variables": {
		"factoryId": "[concat('Microsoft.DataFactory/factories/', parameters('factoryName'))]"
	},
	"resources": [
		{
			"name": "[concat(parameters('factoryName'), '/MIS_Choice_Pax_Bags')]",
			"type": "Microsoft.DataFactory/factories/datasets",
			"apiVersion": "2018-06-01",
			"properties": {
				"linkedServiceName": {
					"referenceName": "eal_main_blob_connection",
					"type": "LinkedServiceReference"
				},
				"folder": {
					"name": "Azure blob"
				},
				"annotations": [],
				"type": "Json",
				"typeProperties": {
					"location": {
						"type": "AzureBlobStorageLocation",
						"fileName": "MIS_Choice_Pax_Bags",
						"folderPath": "test",
						"container": "mis-choice"
					}
				},
				"schema": {
					"type": "object",
					"properties": {
						"Flight": {
							"type": "object",
							"properties": {
								"ID": {
									"type": "string"
								},
								"SegmentNo": {
									"type": "integer"
								},
								"ExternalID": {
									"type": "string"
								},
								"CarrierCode": {
									"type": "string"
								},
								"FlightNo": {
									"type": "string"
								},
								"MarketingCarrierCode": {
									"type": "string"
								},
								"MarketingFlightNo": {
									"type": "string"
								},
								"Type": {
									"type": "string"
								},
								"TailNo": {
									"type": "string"
								},
								"OriginIATA": {
									"type": "string"
								},
								"OriginICAO": {
									"type": "string"
								},
								"OriginAirportName": {
									"type": "string"
								},
								"OriginAirportCity": {
									"type": "string"
								},
								"OriginAirportCountryCode": {
									"type": "string"
								},
								"DepartureTerminal": {
									"type": "string"
								},
								"DepartureGate": {
									"type": "string"
								},
								"DestinationIATA": {
									"type": "string"
								},
								"DestinationICAO": {
									"type": "string"
								},
								"DestinationAirportName": {
									"type": "string"
								},
								"DestinationAirportCity": {
									"type": "string"
								},
								"DestinationAirportCountryCode": {
									"type": "string"
								},
								"ArrivalTerminal": {
									"type": "string"
								},
								"ArrivalGate": {
									"type": "string"
								},
								"ScheduledDepartureTime": {
									"type": "string"
								},
								"ScheduledDepartureTimeUTC": {
									"type": "string"
								},
								"EstimatedDepartureTime": {
									"type": "string"
								},
								"ScheduledArrivalTime": {
									"type": "string"
								},
								"EstimatedArrivalTime": {
									"type": "string"
								},
								"BoardingTime": {
									"type": "string"
								},
								"Message": {
									"type": "string"
								},
								"Status": {
									"type": "string"
								},
								"EnablePassengerAPIS": {
									"type": "boolean"
								},
								"EnableCrewAPIS": {
									"type": "boolean"
								},
								"EnableDCS": {
									"type": "boolean"
								},
								"WeightUnitsKgs": {
									"type": "boolean"
								},
								"IsOpenSeating": {
									"type": "boolean"
								},
								"IsProgressiveFlight": {
									"type": "boolean"
								},
								"EnableThroughCheckIn": {
									"type": "boolean"
								},
								"EnableIatciCheckIn": {
									"type": "boolean"
								},
								"EnableBoarding": {
									"type": "boolean"
								},
								"UseAveragePaxWeight": {
									"type": "boolean"
								},
								"UseAverageBagWeight": {
									"type": "boolean"
								},
								"PnlImported": {
									"type": "boolean"
								},
								"IsCancelled": {
									"type": "boolean"
								},
								"CancelledBy": {
									"type": "string"
								},
								"CancelledReason": {
									"type": "string"
								},
								"IsLocked": {
									"type": "boolean"
								},
								"LockedBy": {
									"type": "string"
								},
								"LockedReason": {
									"type": "string"
								},
								"AircraftCapacity": {
									"type": "integer"
								},
								"BookedPassengersCount": {
									"type": "integer"
								},
								"TotalCargoLoad": {
									"type": "integer"
								},
								"UpliftFuelLoad": {
									"type": "integer"
								},
								"TotalFuelLoad": {
									"type": "integer"
								},
								"RemainingFuelLoad": {
									"type": "integer"
								},
								"Carrier": {
									"type": "object",
									"properties": {
										"CarrierName": {
											"type": "string"
										},
										"Code": {
											"type": "string"
										},
										"IATA": {
											"type": "string"
										},
										"ICAO": {
											"type": "string"
										},
										"ApisCarrierCode": {
											"type": "string"
										},
										"IataMessagingCode": {
											"type": "string"
										},
										"Prefix": {
											"type": "string"
										},
										"Address": {
											"type": "object",
											"properties": {
												"ID": {
													"type": "string"
												},
												"Location": {
													"type": "string"
												},
												"Street1": {
													"type": "string"
												},
												"Street2": {
													"type": "string"
												},
												"City": {
													"type": "string"
												},
												"StateCode": {
													"type": "string"
												},
												"PostalCode": {
													"type": "string"
												},
												"CountryCode": {
													"type": "string"
												},
												"CustomData": {
													"type": "object",
													"properties": {
														"Properties": {
															"type": "object"
														}
													}
												}
											}
										},
										"Email": {
											"type": "string"
										},
										"Website": {
											"type": "string"
										},
										"Logo": {
											"type": "string"
										},
										"Icon": {
											"type": "string"
										},
										"DefaultFlightType": {
											"type": "integer"
										},
										"DefaultIsTestEnvironment": {
											"type": "boolean"
										},
										"DefaultIsOpenSeating": {
											"type": "boolean"
										},
										"DefaultIsEnableBSMs": {
											"type": "boolean"
										},
										"DefaultIsProgressiveFlight": {
											"type": "boolean"
										},
										"DefaultEnableThroughCheckIn": {
											"type": "boolean"
										},
										"DefaultEnableIatciCheckIn": {
											"type": "boolean"
										},
										"DefaultDomesticBoardingTime": {
											"type": "integer"
										},
										"DefaultInternationalBoardingTime": {
											"type": "integer"
										},
										"DefaultWeightUnitsKgs": {
											"type": "boolean"
										},
										"DefaultUseAveragePaxWeight": {
											"type": "boolean"
										},
										"DefaultUseAverageBagWeight": {
											"type": "boolean"
										},
										"DefaultAdultAge": {
											"type": "integer"
										},
										"DefaultAverageAdultMaleWeight": {
											"type": "integer"
										},
										"DefaultAverageAdultFemaleWeight": {
											"type": "integer"
										},
										"DefaultChildAge": {
											"type": "integer"
										},
										"SeatMapChildAge": {
											"type": "integer"
										},
										"DefaultAverageChildWeight": {
											"type": "integer"
										},
										"DefaultPassengerPaddedWeight": {
											"type": "integer"
										},
										"HeavyBagAverageWeight": {
											"type": "integer"
										},
										"HeavyBagThresholdWeight": {
											"type": "integer"
										},
										"LifBagWeightCoefficientType": {
											"type": "integer"
										},
										"LifBagAverageWeight": {
											"type": "number"
										},
										"DefaultCurrencyCode": {
											"type": "string"
										},
										"CurrencyConversionRounding": {
											"type": "integer"
										},
										"ApisSenderID": {
											"type": "string"
										},
										"ApisContactName": {
											"type": "string"
										},
										"ApisTelephone": {
											"type": "string"
										},
										"ApisFax": {
											"type": "string"
										},
										"ApisEmail": {
											"type": "string"
										},
										"TsaPreCheck": {
											"type": "boolean"
										},
										"PnlImportCloseTime": {
											"type": "integer"
										},
										"AdlImportCloseTime": {
											"type": "integer"
										},
										"PermanentlyDeleteCancelledReservationsOnManifestImport": {
											"type": "boolean"
										},
										"DefaultResidenceToNationalityOnManifestImport": {
											"type": "boolean"
										},
										"IncludePassengerIdElementOnIataMessages": {
											"type": "boolean"
										},
										"PrintFlightMessageOnBP": {
											"type": "boolean"
										},
										"PrintOperatedByOnBP": {
											"type": "boolean"
										},
										"PrintSSRsOnBP": {
											"type": "boolean"
										},
										"PrintDocsOkForVerifiedPassengersOnBP": {
											"type": "boolean"
										},
										"PrintReturnConnectingFlightBP": {
											"type": "boolean"
										},
										"PrintBagWeightOnBT": {
											"type": "boolean"
										},
										"IsPrintingBagTagWithoutCheckInAllowed": {
											"type": "boolean"
										},
										"AllowBagsWithNoWeight": {
											"type": "boolean"
										},
										"AllowPermanentDeleteNonPrintedBags": {
											"type": "boolean"
										},
										"MaximumPassengerBags": {
											"type": "integer"
										},
										"EmergencySeatInstructions": {
											"type": "string"
										},
										"PremiumSeatInstructions": {
											"type": "string"
										},
										"EmergencySeatGateStopInstructions": {
											"type": "string"
										},
										"SelecteeGateStopInstructions": {
											"type": "string"
										},
										"UnverifiedDocumentsGateStopInstructions": {
											"type": "string"
										},
										"WatchlistNoFlyMatchInstructions": {
											"type": "string"
										},
										"WatchlistPreventMatchInstructions": {
											"type": "string"
										},
										"WatchlistSelecteeMatchInstructions": {
											"type": "string"
										},
										"EmailSenderAddress": {
											"type": "string"
										},
										"IsBoardingPassPrintWithUnpaidAncillariesAllowed": {
											"type": "boolean"
										},
										"CustomData": {
											"type": "object",
											"properties": {
												"Properties": {
													"type": "object"
												}
											}
										}
									}
								},
								"AncillaryTemplateID": {
									"type": "string"
								},
								"CustomerID": {
									"type": "string"
								},
								"ApiInterfaceIDs": {
									"type": "string"
								},
								"BatchPassengerMask": {
									"type": "string"
								},
								"BatchCrewMemberMask": {
									"type": "string"
								},
								"PreDepartureCloseOutPassengerMask": {
									"type": "string"
								},
								"PostDepartureCloseOutPassengerMask": {
									"type": "string"
								},
								"PreDepartureCloseOutCrewMemberMask": {
									"type": "string"
								},
								"PostDepartureCloseOutCrewMemberMask": {
									"type": "string"
								},
								"PaxFlightPreDepartureCloseOutStatus": {
									"type": "string"
								},
								"PaxFlightPostDepartureCloseOutStatus": {
									"type": "string"
								},
								"CrewFlightPreDepartureCloseOutStatus": {
									"type": "string"
								},
								"CrewFlightPostDepartureCloseOutStatus": {
									"type": "string"
								},
								"PaxBatchPreVetStatus": {
									"type": "string"
								},
								"HasPassengerSecurityTransactions": {
									"type": "boolean"
								},
								"HealthCheckRule": {
									"type": "object",
									"properties": {
										"ID": {
											"type": "string"
										},
										"CarrierCode": {
											"type": "string"
										},
										"OriginCountryEntity": {
											"type": "string"
										},
										"DestinationCountryEntity": {
											"type": "string"
										},
										"OriginAirport": {
											"type": "string"
										},
										"DestinationAirport": {
											"type": "string"
										},
										"Instructions": {
											"type": "string"
										},
										"IsClearToBoard": {
											"type": "boolean"
										},
										"IsRequirePassengerAttestation": {
											"type": "boolean"
										},
										"AttestationMinorStartAge": {
											"type": "integer"
										},
										"AttestationMinorEndAge": {
											"type": "integer"
										},
										"IsRequireProofForRemoteCheckIn": {
											"type": "boolean"
										},
										"IsRequireRemarksForFailStatus": {
											"type": "boolean"
										},
										"IsActive": {
											"type": "boolean"
										},
										"CreatedBy": {
											"type": "string"
										},
										"CreatedTimestampUTC": {
											"type": "string"
										},
										"UpdatedBy": {
											"type": "string"
										}
									}
								},
								"IsNotificationAlertsOptional": {
									"type": "boolean"
								},
								"IsContactTracingOptional": {
									"type": "boolean"
								},
								"IsHealthCheckVerificationOptional": {
									"type": "boolean"
								},
								"IsHealthCheckAttestationOptional": {
									"type": "boolean"
								},
								"IsTestEnvironment": {
									"type": "boolean"
								},
								"CheckedInPassengersCount": {
									"type": "integer"
								},
								"CheckedBagsCount": {
									"type": "integer"
								},
								"CustomData": {
									"type": "object",
									"properties": {
										"Properties": {
											"type": "object"
										}
									}
								}
							}
						},
						"Success": {
							"type": "boolean"
						}
					}
				}
			},
			"dependsOn": []
		},
		{
			"name": "[concat(parameters('factoryName'), '/MIS_Choice_paxdata_test_file')]",
			"type": "Microsoft.DataFactory/factories/datasets",
			"apiVersion": "2018-06-01",
			"properties": {
				"linkedServiceName": {
					"referenceName": "eal_main_blob_connection",
					"type": "LinkedServiceReference"
				},
				"annotations": [],
				"type": "Json",
				"typeProperties": {
					"location": {
						"type": "AzureBlobStorageLocation",
						"folderPath": "test",
						"container": "mis-choice"
					}
				},
				"schema": {}
			},
			"dependsOn": []
		},
		{
			"name": "[concat(parameters('factoryName'), '/MIS_Choice_paxinfo_test')]",
			"type": "Microsoft.DataFactory/factories/datasets",
			"apiVersion": "2018-06-01",
			"properties": {
				"linkedServiceName": {
					"referenceName": "MIS_Choice_REST",
					"type": "LinkedServiceReference"
				},
				"annotations": [],
				"type": "RestResource",
				"typeProperties": {
					"relativeUrl": "passengers/GetPassengersByFlightID?flightID=2b944650-b20e-ec11-aa0e-005056010094&flightSegmentNo=1&includeBags=false&includeAncillaries=false&includeBagTracking=false"
				},
				"schema": []
			},
			"dependsOn": []
		},
		{
			"name": "[concat(parameters('factoryName'), '/RADIXX_DESTINATION_TCN_FILE')]",
			"type": "Microsoft.DataFactory/factories/datasets",
			"apiVersion": "2018-06-01",
			"properties": {
				"linkedServiceName": {
					"referenceName": "eal_main_blob_connection",
					"type": "LinkedServiceReference"
				},
				"folder": {
					"name": "Azure blob"
				},
				"annotations": [],
				"type": "DelimitedText",
				"typeProperties": {
					"location": {
						"type": "AzureBlobStorageLocation",
						"container": "radixx-destination-tcn"
					},
					"columnDelimiter": "",
					"escapeChar": "\\",
					"quoteChar": "\""
				},
				"schema": []
			},
			"dependsOn": []
		},
		{
			"name": "[concat(parameters('factoryName'), '/RADIXX_SOURCE_TCN_FILE')]",
			"type": "Microsoft.DataFactory/factories/datasets",
			"apiVersion": "2018-06-01",
			"properties": {
				"linkedServiceName": {
					"referenceName": "eal_main_blob_connection",
					"type": "LinkedServiceReference"
				},
				"folder": {
					"name": "Azure blob"
				},
				"annotations": [],
				"type": "DelimitedText",
				"typeProperties": {
					"location": {
						"type": "AzureBlobStorageLocation",
						"container": "radixx-source-tcn"
					},
					"columnDelimiter": "",
					"escapeChar": "\\",
					"quoteChar": "\""
				},
				"schema": []
			},
			"dependsOn": []
		},
		{
			"name": "[concat(parameters('factoryName'), '/SF_FLT_CMBandSTDnbrs')]",
			"type": "Microsoft.DataFactory/factories/datasets",
			"apiVersion": "2018-06-01",
			"properties": {
				"linkedServiceName": {
					"referenceName": "eal_edw_connection",
					"type": "LinkedServiceReference"
				},
				"annotations": [],
				"type": "AzureSqlTable",
				"schema": [],
				"typeProperties": {
					"schema": "dbo",
					"table": "SF_FLIGHT_TEST"
				}
			},
			"dependsOn": []
		},
		{
			"name": "[concat(parameters('factoryName'), '/SF_source_airport')]",
			"type": "Microsoft.DataFactory/factories/datasets",
			"apiVersion": "2018-06-01",
			"properties": {
				"linkedServiceName": {
					"referenceName": "eal_main_blob_connection",
					"type": "LinkedServiceReference"
				},
				"folder": {
					"name": "Azure blob"
				},
				"annotations": [],
				"type": "Json",
				"typeProperties": {
					"location": {
						"type": "AzureBlobStorageLocation",
						"fileName": {
							"value": "@concat(concat('bi-flights-',split(utcnow(),'T')[0]),'.json')",
							"type": "Expression"
						},
						"container": "sf-source-airport"
					}
				},
				"schema": {
					"type": "object",
					"properties": {
						"airport_id": {
							"type": "integer"
						},
						"iata_code": {
							"type": "string"
						},
						"icao_code": {
							"type": "string"
						},
						"faa_code": {
							"type": "string"
						},
						"airport_name": {
							"type": "string"
						},
						"city_name": {
							"type": "string"
						},
						"state_code": {
							"type": "string"
						},
						"country_code": {
							"type": "string"
						},
						"weather_zone": {
							"type": "string"
						},
						"latitude": {
							"type": "string"
						},
						"longitude": {
							"type": "string"
						},
						"elevation_feet": {
							"type": "integer"
						},
						"iana_timezone": {
							"type": "string"
						},
						"is_base": {
							"type": "boolean"
						},
						"base_initial": {
							"type": "null"
						},
						"is_active": {
							"type": "boolean"
						},
						"is_deleted": {
							"type": "boolean"
						}
					}
				}
			},
			"dependsOn": []
		},
		{
			"name": "[concat(parameters('factoryName'), '/SF_source_bi_airport')]",
			"type": "Microsoft.DataFactory/factories/datasets",
			"apiVersion": "2018-06-01",
			"properties": {
				"linkedServiceName": {
					"referenceName": "SkedFlexConnection",
					"type": "LinkedServiceReference"
				},
				"folder": {
					"name": "Source"
				},
				"annotations": [],
				"type": "PostgreSqlTable",
				"schema": [],
				"typeProperties": {
					"schema": "bi",
					"table": "airport"
				}
			},
			"dependsOn": []
		},
		{
			"name": "[concat(parameters('factoryName'), '/SF_source_bi_equip_sched')]",
			"type": "Microsoft.DataFactory/factories/datasets",
			"apiVersion": "2018-06-01",
			"properties": {
				"linkedServiceName": {
					"referenceName": "SkedFlexConnection",
					"type": "LinkedServiceReference"
				},
				"folder": {
					"name": "Source"
				},
				"annotations": [],
				"type": "PostgreSqlTable",
				"schema": [],
				"typeProperties": {
					"schema": "bi",
					"table": "equipment_sched"
				}
			},
			"dependsOn": []
		},
		{
			"name": "[concat(parameters('factoryName'), '/SF_source_bi_flight')]",
			"type": "Microsoft.DataFactory/factories/datasets",
			"apiVersion": "2018-06-01",
			"properties": {
				"linkedServiceName": {
					"referenceName": "SkedFlexConnection",
					"type": "LinkedServiceReference"
				},
				"folder": {
					"name": "Source"
				},
				"annotations": [],
				"type": "PostgreSqlTable",
				"schema": [],
				"typeProperties": {
					"schema": "bi",
					"table": "flight"
				}
			},
			"dependsOn": []
		},
		{
			"name": "[concat(parameters('factoryName'), '/SF_source_bi_flight_crew')]",
			"type": "Microsoft.DataFactory/factories/datasets",
			"apiVersion": "2018-06-01",
			"properties": {
				"linkedServiceName": {
					"referenceName": "SkedFlexConnection",
					"type": "LinkedServiceReference"
				},
				"folder": {
					"name": "Source"
				},
				"annotations": [],
				"type": "PostgreSqlTable",
				"schema": [],
				"typeProperties": {
					"schema": "bi",
					"table": "flight_crew"
				}
			},
			"dependsOn": []
		},
		{
			"name": "[concat(parameters('factoryName'), '/SF_source_bi_flight_delay')]",
			"type": "Microsoft.DataFactory/factories/datasets",
			"apiVersion": "2018-06-01",
			"properties": {
				"linkedServiceName": {
					"referenceName": "SkedFlexConnection",
					"type": "LinkedServiceReference"
				},
				"folder": {
					"name": "Source"
				},
				"annotations": [],
				"type": "PostgreSqlTable",
				"schema": [],
				"typeProperties": {
					"schema": "bi",
					"table": "flight_delay"
				}
			},
			"dependsOn": []
		},
		{
			"name": "[concat(parameters('factoryName'), '/SF_source_bi_pairing')]",
			"type": "Microsoft.DataFactory/factories/datasets",
			"apiVersion": "2018-06-01",
			"properties": {
				"linkedServiceName": {
					"referenceName": "SkedFlexConnection",
					"type": "LinkedServiceReference"
				},
				"folder": {
					"name": "Source"
				},
				"annotations": [],
				"type": "PostgreSqlTable",
				"schema": [],
				"typeProperties": {
					"schema": "bi",
					"table": "pairing"
				}
			},
			"dependsOn": []
		},
		{
			"name": "[concat(parameters('factoryName'), '/SF_source_bi_pairing_item')]",
			"type": "Microsoft.DataFactory/factories/datasets",
			"apiVersion": "2018-06-01",
			"properties": {
				"linkedServiceName": {
					"referenceName": "SkedFlexConnection",
					"type": "LinkedServiceReference"
				},
				"folder": {
					"name": "Source"
				},
				"annotations": [],
				"type": "PostgreSqlTable",
				"schema": [],
				"typeProperties": {
					"schema": "bi",
					"table": "pairing_item"
				}
			},
			"dependsOn": []
		},
		{
			"name": "[concat(parameters('factoryName'), '/SF_source_bi_shift')]",
			"type": "Microsoft.DataFactory/factories/datasets",
			"apiVersion": "2018-06-01",
			"properties": {
				"linkedServiceName": {
					"referenceName": "SkedFlexConnection",
					"type": "LinkedServiceReference"
				},
				"folder": {
					"name": "Source"
				},
				"annotations": [],
				"type": "PostgreSqlTable",
				"schema": [],
				"typeProperties": {
					"schema": "bi",
					"table": "shift"
				}
			},
			"dependsOn": []
		},
		{
			"name": "[concat(parameters('factoryName'), '/SF_source_bi_user')]",
			"type": "Microsoft.DataFactory/factories/datasets",
			"apiVersion": "2018-06-01",
			"properties": {
				"linkedServiceName": {
					"referenceName": "SkedFlexConnection",
					"type": "LinkedServiceReference"
				},
				"folder": {
					"name": "Source"
				},
				"annotations": [],
				"type": "PostgreSqlTable",
				"schema": [],
				"typeProperties": {
					"schema": "bi",
					"table": "user"
				}
			},
			"dependsOn": []
		},
		{
			"name": "[concat(parameters('factoryName'), '/SF_source_bi_user_category')]",
			"type": "Microsoft.DataFactory/factories/datasets",
			"apiVersion": "2018-06-01",
			"properties": {
				"linkedServiceName": {
					"referenceName": "SkedFlexConnection",
					"type": "LinkedServiceReference"
				},
				"folder": {
					"name": "Source"
				},
				"annotations": [],
				"type": "PostgreSqlTable",
				"schema": [],
				"typeProperties": {
					"schema": "bi",
					"table": "user_category"
				}
			},
			"dependsOn": []
		},
		{
			"name": "[concat(parameters('factoryName'), '/SF_source_delays')]",
			"type": "Microsoft.DataFactory/factories/datasets",
			"apiVersion": "2018-06-01",
			"properties": {
				"linkedServiceName": {
					"referenceName": "eal_main_blob_connection",
					"type": "LinkedServiceReference"
				},
				"folder": {
					"name": "Azure blob"
				},
				"annotations": [],
				"type": "Json",
				"typeProperties": {
					"location": {
						"type": "AzureBlobStorageLocation",
						"fileName": {
							"value": "@concat(concat('bi-flights-',split(utcnow(),'T')[0]),'.json')",
							"type": "Expression"
						},
						"container": "sf-source-delays"
					}
				},
				"schema": {
					"type": "object",
					"properties": {
						"flight_id": {
							"type": "integer"
						},
						"delay_type": {
							"type": "string"
						},
						"duration_mins": {
							"type": "integer"
						},
						"delay_code": {
							"type": "string"
						},
						"delay_code_name": {
							"type": "string"
						}
					}
				}
			},
			"dependsOn": []
		},
		{
			"name": "[concat(parameters('factoryName'), '/SF_source_equip_sched')]",
			"type": "Microsoft.DataFactory/factories/datasets",
			"apiVersion": "2018-06-01",
			"properties": {
				"linkedServiceName": {
					"referenceName": "eal_main_blob_connection",
					"type": "LinkedServiceReference"
				},
				"folder": {
					"name": "Azure blob"
				},
				"annotations": [],
				"type": "Json",
				"typeProperties": {
					"location": {
						"type": "AzureBlobStorageLocation",
						"fileName": {
							"value": "@concat(concat('bi-flights-',split(utcnow(),'T')[0]),'.json')",
							"type": "Expression"
						},
						"container": "sf-source-equip-sched"
					}
				},
				"schema": {
					"type": "object",
					"properties": {
						"eqp_sched_id": {
							"type": "integer"
						},
						"ac_registration": {
							"type": "string"
						},
						"status_code": {
							"type": "string"
						},
						"status_name": {
							"type": "string"
						},
						"status_description": {
							"type": "string"
						},
						"start_time": {
							"type": "string"
						},
						"end_time": {
							"type": "string"
						},
						"notes": {
							"type": "string"
						},
						"is_deleted": {
							"type": "boolean"
						},
						"updated_at": {
							"type": "string"
						}
					}
				}
			},
			"dependsOn": []
		},
		{
			"name": "[concat(parameters('factoryName'), '/SF_source_flight_crew')]",
			"type": "Microsoft.DataFactory/factories/datasets",
			"apiVersion": "2018-06-01",
			"properties": {
				"linkedServiceName": {
					"referenceName": "eal_main_blob_connection",
					"type": "LinkedServiceReference"
				},
				"folder": {
					"name": "Azure blob"
				},
				"annotations": [],
				"type": "Json",
				"typeProperties": {
					"location": {
						"type": "AzureBlobStorageLocation",
						"fileName": {
							"value": "@concat(concat('bi-flight-crew-',split(utcnow(),'T')[0]),'.json')",
							"type": "Expression"
						},
						"container": "sf-source-user-category"
					}
				},
				"schema": {}
			},
			"dependsOn": []
		}
	]
}